lambda_packager/__init__.py
lambda_packager/config.py
lambda_packager/custom_log_formatter.py
lambda_packager/handle_poetry.py
lambda_packager/handle_requirements_txt.py
lambda_packager/package.py
lambda_packager-1.2.2.dist-info/LICENSE
lambda_packager-1.2.2.dist-info/METADATA
lambda_packager-1.2.2.dist-info/WHEEL
lambda_packager-1.2.2.dist-info/entry_points.txt
lambda_packager-1.2.2.dist-info/RECORD
