Metadata-Version: 2.1
Name: lambda-packager
Version: 1.2.2
Summary: Stop writing your own scripts and let this package your python aws lambda zips for you
Home-page: https://github.com/hmrc/python-aws-lambda-packager
License: Apache-2.0
Author: cob16
Author-email: public+github@cormacbrady.info
Requires-Python: >=3.8.0,<4.0.0
Classifier: License :: OSI Approved :: Apache Software License
Classifier: Programming Language :: Python :: 3
Classifier: Programming Language :: Python :: 3.8
Classifier: Programming Language :: Python :: 3.9
Classifier: Programming Language :: Python :: 3.10
Classifier: Programming Language :: Python :: 3.11
Requires-Dist: tomli (>=2.0.1,<3.0.0)
Project-URL: Repository, https://github.com/hmrc/python-aws-lambda-packager
